tno/mpc/encryption_schemes/paillier/__init__.py
tno/mpc/encryption_schemes/paillier/paillier.py
tno/mpc/encryption_schemes/paillier/py.typed
tno/mpc/encryption_schemes/paillier/test/__init__.py
tno/mpc/encryption_schemes/paillier/test/conftest.py
tno/mpc/encryption_schemes/paillier/test/test_integration_communication.py
tno/mpc/encryption_schemes/paillier/test/test_paillier.py
tno/mpc/encryption_schemes/paillier/test/test_serialization.py
tno_mpc_encryption_schemes_paillier-4.1.0.dist-info/licenses/LICENSE
tno_mpc_encryption_schemes_paillier-4.1.0.dist-info/METADATA
tno_mpc_encryption_schemes_paillier-4.1.0.dist-info/WHEEL
tno_mpc_encryption_schemes_paillier-4.1.0.dist-info/top_level.txt
tno_mpc_encryption_schemes_paillier-4.1.0.dist-info/RECORD
