Metadata-Version: 2.4
Name: tno.mpc.encryption_schemes.paillier
Version: 4.1.0
Summary: Implementation of the Paillier cryptosystem
Author-email: TNO PET Lab <petlab@tno.nl>
Maintainer-email: TNO PET Lab <petlab@tno.nl>
License: Apache License, Version 2.0
Project-URL: Homepage, https://pet.tno.nl/
Project-URL: Documentation, https://docs.pet.tno.nl/mpc/encryption_schemes/paillier/4.1.0
Project-URL: Source, https://github.com/TNO-MPC/encryption_schemes.paillier
Keywords: TNO,MPC,multi-party computation,encryption schemes,paillier,cryptosystem
Platform: any
Classifier: License :: OSI Approved :: Apache Software License
Classifier: Programming Language :: Python :: 3
Classifier: Operating System :: OS Independent
Classifier: Intended Audience :: Developers
Classifier: Intended Audience :: Information Technology
Classifier: Intended Audience :: Science/Research
Classifier: Typing :: Typed
Classifier: Topic :: Security :: Cryptography
Requires-Python: >=3.9
License-File: LICENSE
Requires-Dist: tno.mpc.encryption_schemes.templates~=5.0
Requires-Dist: tno.mpc.encryption_schemes.utils~=0.16
Requires-Dist: typing_extensions~=4.0; python_version < "3.11"
Provides-Extra: gmpy
Requires-Dist: tno.mpc.encryption_schemes.utils[gmpy]; extra == "gmpy"
Provides-Extra: communication
Requires-Dist: tno.mpc.communication~=5.0; extra == "communication"
Requires-Dist: tno.mpc.encryption_schemes.utils[communication]; extra == "communication"
Provides-Extra: tests
Requires-Dist: tno.mpc.encryption_schemes.paillier[communication]; extra == "tests"
Requires-Dist: tno.mpc.communication[pytest]; extra == "tests"
Requires-Dist: pytest>=8.1; extra == "tests"
Dynamic: license-file
